[{"ENTITY_1": "Nature's Bounty Natural Vitamin B1", "CONNECTION": "helped with", "ENTITY_2": "leg cramps"}, {"ENTITY_1": "Nature's Bounty Natural Vitamin B1", "CONNECTION": "good price and great", "ENTITY_2": "product"}, {"ENTITY_1": "Nature's Bounty Natural Vitamin B1", "CONNECTION": "nourish the nerves and make joints feel smoother", "ENTITY_2": "mom"}, {"ENTITY_1": "Nature's Bounty Natural Vitamin B1", "CONNECTION": "hard to find in most stores", "ENTITY_2": "Great"}, {"ENTITY_1": "Nature's Bounty Natural Vitamin B1", "CONNECTION": "perfect shape", "ENTITY_2": "arrived"}]