[{"ENTITY_1": "Tums", "CONNECTION": "old", "ENTITY_2": "products"}, {"ENTITY_1": "Tums", "CONNECTION": "dried out", "ENTITY_2": "products"}, {"ENTITY_1": "Tums", "CONNECTION": "over priced", "ENTITY_2": "products"}, {"ENTITY_1": "Tums", "CONNECTION": "chewy", "ENTITY_2": "delight"}, {"ENTITY_1": "Tums", "CONNECTION": "great", "ENTITY_2": "product"}, {"ENTITY_1": "Tums", "CONNECTION": "very cherry", "ENTITY_2": "taste"}, {"ENTITY_1": "Tums", "CONNECTION": "rapid", "ENTITY_2": "antacid relief"}, {"ENTITY_1": "Tums", "CONNECTION": "over priced", "ENTITY_2": "product"}]