[{"ENTITY_1": "straws", "CONNECTION": "are", "ENTITY_2": "gold"}, {"ENTITY_1": "straws", "CONNECTION": "are", "ENTITY_2": "faded"}, {"ENTITY_1": "straws", "CONNECTION": "are", "ENTITY_2": "transparent"}, {"ENTITY_1": "straws", "CONNECTION": "are", "ENTITY_2": "thin"}, {"ENTITY_1": "straws", "CONNECTION": "are", "ENTITY_2": "sturdy"}, {"ENTITY_1": "straws", "CONNECTION": "are", "ENTITY_2": "cute"}, {"ENTITY_1": "straws", "CONNECTION": "are", "ENTITY_2": "nice color"}, {"ENTITY_1": "straws", "CONNECTION": "are", "ENTITY_2": "not gold"}, {"ENTITY_1": "straws", "CONNECTION": "are", "ENTITY_2": "ugly green"}, {"ENTITY_1": "straws", "CONNECTION": "are", "ENTITY_2": "light, muted gold"}, {"ENTITY_1": "straws", "CONNECTION": "are", "ENTITY_2": "dingy gold color"}]