[{"ENTITY_1": "supplements", "CONNECTION": "help", "ENTITY_2": "hair growth"}, {"ENTITY_1": "supplements", "CONNECTION": "help", "ENTITY_2": "hair"}, {"ENTITY_1": "supplements", "CONNECTION": "help", "ENTITY_2": "nails"}, {"ENTITY_1": "supplements", "CONNECTION": "help", "ENTITY_2": "skin"}, {"ENTITY_1": "supplements", "CONNECTION": "help", "ENTITY_2": "stop hair loss"}, {"ENTITY_1": "supplements", "CONNECTION": "promote", "ENTITY_2": "thicker hair"}, {"ENTITY_1": "supplements", "CONNECTION": "promote", "ENTITY_2": "longer hair"}, {"ENTITY_1": "supplements", "CONNECTION": "promote", "ENTITY_2": "stronger hair"}, {"ENTITY_1": "supplements", "CONNECTION": "promote", "ENTITY_2": "healthy skin"}, {"ENTITY_1": "supplements", "CONNECTION": "promote", "ENTITY_2": "quick hair growth"}, {"ENTITY_1": "supplements", "CONNECTION": "promote", "ENTITY_2": "new hair growth"}]