[{"ENTITY_1": "AF4TI755Q4BV632PMF64DJGXOUQQ", "CONNECTION": "reviewed", "ENTITY_2": "B07Q2FT772"}, {"ENTITY_1": "AF4TI755Q4BV632PMF64DJGXOUQQ", "CONNECTION": "rated", "ENTITY_2": "5.0 out of 5"}, {"ENTITY_1": "AF4TI755Q4BV632PMF64DJGXOUQQ", "CONNECTION": "reviewed", "ENTITY_2": "Texas SuperFood - Hip Knee & Joint Support"}, {"ENTITY_1": "Texas SuperFood - Hip Knee & Joint Support", "CONNECTION": "contains", "ENTITY_2": "Turmeric and Curcumin"}, {"ENTITY_1": "Texas SuperFood - Hip Knee & Joint Support", "CONNECTION": "contains", "ENTITY_2": "Hydrolyzed Collagen"}, {"ENTITY_1": "Texas SuperFood - Hip Knee & Joint Support", "CONNECTION": "supports", "ENTITY_2": "Joints & Connective Tissue"}, {"ENTITY_1": "Texas SuperFood - Hip Knee & Joint Support", "CONNECTION": "is", "ENTITY_2": "Antiinflammatory Supplements"}, {"ENTITY_1": "Texas SuperFood - Hip Knee & Joint Support", "CONNECTION": "has", "ENTITY_2": "90 Capsules"}]