[{"ENTITY_1": "ASIN", "CONNECTION": "is", "ENTITY_2": "B07RTB9JJD"}, {"ENTITY_1": "Review Title", "CONNECTION": "is", "ENTITY_2": "Original Cod Liver Oil Shaped Capsules"}, {"ENTITY_1": "Review Text", "CONNECTION": "is", "ENTITY_2": "Great value and super fast delivery"}, {"ENTITY_1": "Rating", "CONNECTION": "is", "ENTITY_2": "5.0 out of 5"}, {"ENTITY_1": "User", "CONNECTION": "is", "ENTITY_2": "AFCYS5MYNYR7ZL7ODTIAASSDHTXA"}, {"ENTITY_1": "Item Title", "CONNECTION": "is", "ENTITY_2": "KetoLiving Cod Liver Oil - 1000 mg, 270 Softgels - Powerful Source of Omega-3 Fatty Acids - Rich in Vitamin A & Vitamin D - Gluten-Free - 90 Servings"}]