[{"ENTITY_1": "Vitamin C chewable", "CONNECTION": "tasty", "ENTITY_2": "It"}, {"ENTITY_1": "Vitamin C chewable", "CONNECTION": "nice flavor", "ENTITY_2": "It"}, {"ENTITY_1": "Vitamin C chewable", "CONNECTION": "take everyday", "ENTITY_2": "I"}, {"ENTITY_1": "Vitamin C Supplement", "CONNECTION": "delivered before", "ENTITY_2": "stated date"}, {"ENTITY_1": "Vitamin C Supplement", "CONNECTION": "pleased with", "ENTITY_2": "product"}, {"ENTITY_1": "Vitamin C Supplement", "CONNECTION": "pleased with", "ENTITY_2": "price"}, {"ENTITY_1": "Vitamin C Supplement", "CONNECTION": "not chewable", "ENTITY_2": "It"}, {"ENTITY_1": "Vitamin C Supplement", "CONNECTION": "too large to swallow", "ENTITY_2": "It"}, {"ENTITY_1": "Vitamin C Supplement", "CONNECTION": "will not purchase again", "ENTITY_2": "I"}, {"ENTITY_1": "Vitamin C Supplement", "CONNECTION": "easy to chew", "ENTITY_2": "It"}, {"ENTITY_1": "Vitamin C Supplement", "CONNECTION": "good for the body", "ENTITY_2": "It"}, {"ENTITY_1": "Vitamin C Supplement", "CONNECTION": "helps support immunity", "ENTITY_2": "It"}, {"ENTITY_1": "Vitamin C Supplement", "CONNECTION": "tastes fine", "ENTITY_2": "It"}, {"ENTITY_1": "Vitamin C Supplement", "CONNECTION": "perfect for family", "ENTITY_2": "someone"}, {"ENTITY_1": "Vitamin C Supplement", "CONNECTION": "good product", "ENTITY_2": "It"}]