[{"ENTITY_1": "product", "CONNECTION": "arrived spoiled", "ENTITY_2": "Buried Treasure Liquid Vitamins"}, {"ENTITY_1": "product", "CONNECTION": "bad taste", "ENTITY_2": "Buried Treasure Liquid Vitamins"}, {"ENTITY_1": "product", "CONNECTION": "excellent", "ENTITY_2": "Buried Treasure Liquid Vitamins"}, {"ENTITY_1": "product", "CONNECTION": "good for animals", "ENTITY_2": "Buried Treasure Liquid Vitamins"}, {"ENTITY_1": "product", "CONNECTION": "take with juice", "ENTITY_2": "Buried Treasure Liquid Vitamins"}, {"ENTITY_1": "product", "CONNECTION": "good liquid vitamins", "ENTITY_2": "Buried Treasure Liquid Vitamins"}, {"ENTITY_1": "product", "CONNECTION": "no more choking down horse size pills", "ENTITY_2": "Buried Treasure Liquid Vitamins"}, {"ENTITY_1": "product", "CONNECTION": "interesting", "ENTITY_2": "Buried Treasure Liquid Vitamins"}, {"ENTITY_1": "product", "CONNECTION": "liquid immune system booster", "ENTITY_2": "Buried Treasure Liquid Vitamins"}, {"ENTITY_1": "product", "CONNECTION": "great vitamins", "ENTITY_2": "Buried Treasure Liquid Vitamins"}, {"ENTITY_1": "product", "CONNECTION": "BEST Liquid vitamin on the market", "ENTITY_2": "Buried Treasure Liquid Vitamins"}]