[{"ENTITY_1": "Lenere Weekly Pill Organizer", "CONNECTION": "has", "ENTITY_2": "Good Size"}, {"ENTITY_1": "Lenere Weekly Pill Organizer", "CONNECTION": "has", "ENTITY_2": "Huge Compartments"}, {"ENTITY_1": "Lenere Weekly Pill Organizer", "CONNECTION": "has", "ENTITY_2": "7-Day / 4-Times-A-Day"}, {"ENTITY_1": "Lenere Weekly Pill Organizer", "CONNECTION": "has", "ENTITY_2": "Plenty of Fish Oils"}, {"ENTITY_1": "Lenere Weekly Pill Organizer", "CONNECTION": "has", "ENTITY_2": "Vitamins"}, {"ENTITY_1": "Lenere Weekly Pill Organizer", "CONNECTION": "has", "ENTITY_2": "Supplement"}, {"ENTITY_1": "Lenere Weekly Pill Organizer", "CONNECTION": "has", "ENTITY_2": "Medication"}]