[{"ENTITY_1": "Gummy candy", "CONNECTION": "good for", "ENTITY_2": "kids"}, {"ENTITY_1": "kids", "CONNECTION": "love", "ENTITY_2": "gummies"}, {"ENTITY_1": "kids", "CONNECTION": "not gotten sick", "ENTITY_2": "since taking gummies"}, {"ENTITY_1": "gummies", "CONNECTION": "contain", "ENTITY_2": "Vitamin C & D"}, {"ENTITY_1": "Vitamin C & D", "CONNECTION": "great for", "ENTITY_2": "health"}, {"ENTITY_1": "gummies", "CONNECTION": "taste", "ENTITY_2": "great"}, {"ENTITY_1": "gummies", "CONNECTION": "sweet", "ENTITY_2": "sugar coated"}, {"ENTITY_1": "gummies", "CONNECTION": "not stuck together", "ENTITY_2": "in jar"}, {"ENTITY_1": "gummies", "CONNECTION": "help in", "ENTITY_2": "overall health"}, {"ENTITY_1": "gummies", "CONNECTION": "asked for", "ENTITY_2": "specifically"}]